pyfdc/__init__.py
pyfdc/__main__.py
pyfdc/pyfdc.py
pyfdc/utils.py
pyfdc/version.py
pyfdc-0.2.2.dist-info/LICENSE
pyfdc-0.2.2.dist-info/METADATA
pyfdc-0.2.2.dist-info/WHEEL
pyfdc-0.2.2.dist-info/top_level.txt
pyfdc-0.2.2.dist-info/RECORD
