Metadata-Version: 2.1
Name: pyfdc
Version: 0.2.2
Summary: A python interface to FoodDataCentral
Home-page: http://www.github.com/Nelson-Gon/pyfdc
Author: Nelson Gonzabato
Author-email: gonzabato@hotmail.com
License: MIT
Download-URL: https://github.com/Nelson-Gon/pyfdc/archive/refs/tags/v0.2.2.zip
Keywords: nutrition food agriculture rest api
Platform: UNKNOWN
Requires-Python: >=3.6
Requires-Dist: requests
Requires-Dist: pandas
